blue_assistant/README.py
blue_assistant/__init__.py
blue_assistant/__main__.py
blue_assistant/config.env
blue_assistant/env.py
blue_assistant/functions.py
blue_assistant/host.py
blue_assistant/logger.py
blue_assistant/sample.env
blue_assistant/urls.py
blue_assistant/.abcli/RAG.sh
blue_assistant/.abcli/abcli.sh
blue_assistant/.abcli/actions.sh
blue_assistant/.abcli/alias.sh
blue_assistant/.abcli/blue_assistant.sh
blue_assistant/.abcli/browse.sh
blue_assistant/.abcli/hue.sh
blue_assistant/.abcli/script.sh
blue_assistant/.abcli/web.sh
blue_assistant/.abcli/RAG/query_pdf.sh
blue_assistant/.abcli/hue/create_user.sh
blue_assistant/.abcli/hue/list.sh
blue_assistant/.abcli/hue/set.sh
blue_assistant/.abcli/script/list.sh
blue_assistant/.abcli/script/run.sh
blue_assistant/.abcli/tests/RAG_query_pdf.sh
blue_assistant/.abcli/tests/README.sh
blue_assistant/.abcli/tests/help.sh
blue_assistant/.abcli/tests/script_list.sh
blue_assistant/.abcli/tests/script_run.sh
blue_assistant/.abcli/tests/version.sh
blue_assistant/.abcli/tests/web_crawl.sh
blue_assistant/.abcli/tests/web_fetch.sh
blue_assistant/.abcli/web/crawl.sh
blue_assistant/.abcli/web/fetch.sh
blue_assistant/help/RAG.py
blue_assistant/help/__init__.py
blue_assistant/help/__main__.py
blue_assistant/help/functions.py
blue_assistant/help/hue.py
blue_assistant/help/script.py
blue_assistant/help/web.py
blue_assistant/script/__init__.py
blue_assistant/script/__main__.py
blue_assistant/script/load.py
blue_assistant/script/actions/__init__.py
blue_assistant/script/actions/generate_image.py
blue_assistant/script/actions/generate_text.py
blue_assistant/script/actions/generic.py
blue_assistant/script/actions/web_crawl.py
blue_assistant/script/repository/__init__.py
blue_assistant/script/repository/functions.py
blue_assistant/script/repository/base/__init__.py
blue_assistant/script/repository/base/classes.py
blue_assistant/script/repository/base/root.py
blue_assistant/script/repository/blue_amo/__init__.py
blue_assistant-4.401.1.dist-info/licenses/LICENSE
blue_assistant-4.401.1.dist-info/METADATA
blue_assistant-4.401.1.dist-info/WHEEL
blue_assistant-4.401.1.dist-info/top_level.txt
blue_assistant-4.401.1.dist-info/RECORD
