Metadata-Version: 2.4
Name: blue_assistant
Version: 4.401.1
Summary: 🧠 An AI Assistant.
Home-page: https://github.com/kamangir/blue-assistant
Author: Arash Abadpour (Kamangir)
Author-email: arash@kamangir.net
License: Public Domain
Classifier: Programming Language :: Python :: 3
Classifier: Programming Language :: Unix Shell
Classifier: License :: Public Domain
Classifier: Operating System :: OS Independent
License-File: LICENSE
Requires-Dist: blueness
Requires-Dist: blue-options
Requires-Dist: abcli
Requires-Dist: openai_commands
Requires-Dist: blueflow
Requires-Dist: boto3
Requires-Dist: openai
Requires-Dist: geojson
Requires-Dist: geopandas
Requires-Dist: matplotlib
Requires-Dist: numpy
Requires-Dist: opencv-python
Requires-Dist: pymysql
Requires-Dist: pyyaml
Requires-Dist: pylint
Requires-Dist: pytest
Requires-Dist: python-dotenv[cli]
Requires-Dist: tqdm
Requires-Dist: beautifulsoup4
Requires-Dist: networkx
Requires-Dist: pydot
Requires-Dist: openai
Requires-Dist: faiss-cpu
Requires-Dist: langchain
Requires-Dist: pypdf2
Requires-Dist: langchain_openai
Requires-Dist: sentence-transformers
Requires-Dist: langchain_community
Dynamic: author
Dynamic: author-email
Dynamic: classifier
Dynamic: description
Dynamic: description-content-type
Dynamic: home-page
Dynamic: license
Dynamic: license-file
Dynamic: requires-dist
Dynamic: summary
